skillsmd/__init__.py
skillsmd/add.py
skillsmd/agents.py
skillsmd/cli.py
skillsmd/constants.py
skillsmd/git.py
skillsmd/init.py
skillsmd/installer.py
skillsmd/list_cmd.py
skillsmd/remove.py
skillsmd/skills.py
skillsmd/source_parser.py
skillsmd/types.py
skillsmd-0.0.2.dist-info/WHEEL
skillsmd-0.0.2.dist-info/entry_points.txt
skillsmd-0.0.2.dist-info/METADATA
skillsmd-0.0.2.dist-info/RECORD
