Metadata-Version: 2.4
Name: skillsmd
Version: 0.0.2
Summary: The open agent skills ecosystem - Python CLI
Keywords: skills,agents,cli,ai,llm
Author: Alessio
Author-email: Alessio <5672748+avvertix@users.noreply.github.com>
License-Expression: MIT
Classifier: Development Status :: 4 - Beta
Classifier: Environment :: Console
Classifier: Intended Audience :: Developers
Classifier: License :: OSI Approved :: MIT License
Classifier: Programming Language :: Python :: 3
Classifier: Programming Language :: Python :: 3.10
Classifier: Programming Language :: Python :: 3.11
Classifier: Programming Language :: Python :: 3.12
Classifier: Topic :: Software Development :: Libraries :: Python Modules
Requires-Dist: typer>=0.9
Requires-Dist: rich>=13.0
Requires-Dist: python-frontmatter>=1.0
Requires-Dist: httpx>=0.25
Requires-Dist: gitpython>=3.1
Requires-Python: >=3.10
Project-URL: Homepage, https://github.com/avvertix/skillsmd
Project-URL: Repository, https://github.com/avvertix/skillsmd
